layout_visualizer/__init__.py
layout_visualizer/fonts/NotoSansJP-Medium.ttf
layout_visualizer/fonts/OFL.txt
layout_visualizer/fonts/README.txt
layout_visualizer/layout_visualizer.py
layout_visualizer/model/bbox.py
layout_visualizer/utils/color.py
layout_visualizer/utils/path.py
layout_visualizer/utils/pillow.py
layout_visualizer-1.0.1.dist-info/METADATA
layout_visualizer-1.0.1.dist-info/WHEEL
layout_visualizer-1.0.1.dist-info/RECORD
