Metadata-Version: 2.1
Name: layout-visualizer
Version: 1.0.1
Summary: Easily draw layout BBoxes
Home-page: https://github.com/shunyooo/layout-visualizer
License: MIT
Author: Shunyo Kawamoto
Author-email: shunyo.kawamoto@gmail.com
Requires-Python: >=3.8,<4.0
Classifier: License :: OSI Approved :: MIT License
Classifier: Programming Language :: Python :: 3
Classifier: Programming Language :: Python :: 3.8
Classifier: Programming Language :: Python :: 3.9
Classifier: Programming Language :: Python :: 3.10
Classifier: Programming Language :: Python :: 3.11
Classifier: Programming Language :: Python :: 3.12
Classifier: Programming Language :: Python :: 3.13
Requires-Dist: pillow (>=10.2.0,<11.0.0)
Requires-Dist: pydantic (>=2.6.3,<3.0.0)
Project-URL: Repository, https://github.com/shunyooo/layout-visualizer
